Metadata-Version: 2.1
Name: dlclib
Version: 1.1.0
Summary: a wrapper of DeepLabCut for its ease of use.
Home-page: https://github.com/gwappa/python-dlclib
Author: Keisuke Sehara
Author-email: keisuke.sehara@gmail.com
License: MIT
Platform: UNKNOWN
Classifier: Development Status :: 3 - Alpha
Classifier: License :: OSI Approved :: MIT License
Classifier: Programming Language :: Python :: 3
Classifier: Intended Audience :: Science/Research
Requires-Python: >=3.6
